{
    "swagger": "2.0",
    "info": {
        "description": "API для управления задачами и категориями",
        "title": "Task Manager API",
        "contact": {},
        "version": "1.0"
    },
    "host": "localhost:8080",
    "basePath": "/",
    "paths": {
        "/register": {
            "post": {
                "description": "Создает нового пользователя в базе",
                "consumes": [
                    "application/json"
                ],
                "produces": [
                    "application/json"
                ],
                "tags": [
                    "Auth"
                ],
                "summary": "Регистрация пользователя",
                "parameters": [
                    {
                        "description": "данные для регистрации",
                        "name": "input",
                        "in": "body",
                        "required": true,
                        "schema": {
                            "$ref": "#/definitions/models.RegisterInput"
                        }
                    }
                ],
                "responses": {
                    "201": {
                        "description": "Created",
                        "schema": {
                            "type": "object",
                            "additionalProperties": true
                        }
                    },
                    "400": {
                        "description": "Bad Request",
                        "schema": {
                            "type": "object",
                            "additionalProperties": {
                                "type": "string"
                            }
                        }
                    },
                    "500": {
                        "description": "Internal Server Error",
                        "schema": {
                            "type": "object",
                            "additionalProperties": {
                                "type": "string"
                            }
                        }
                    }
                }
            }
        }
    },
    "definitions": {
        "models.RegisterInput": {
            "type": "object",
            "required": [
                "email",
                "password"
            ],
            "properties": {
                "email": {
                    "type": "string"
                },
                "password": {
                    "type": "string",
                    "minLength": 8
                }
            }
        }
    }
}